clusterlets/__init__.py
clusterlets/extractors/__init__.py
clusterlets/extractors/measures.py
clusterlets/extractors/clusters/__init__.py
clusterlets/extractors/matches/__init__.py
clusterlets/extractors/matches/graph.py
clusterlets/extractors/matches/partition.py
clusterlets-0.0.1.dist-info/METADATA
clusterlets-0.0.1.dist-info/WHEEL
clusterlets-0.0.1.dist-info/licenses/LICENSE
clusterlets-0.0.1.dist-info/RECORD
