Metadata-Version: 2.4
Name: clusterlets
Version: 0.0.1
Summary: A library for clusterlet induction, that is, sets of fair clusters.
Project-URL: Homepage, https://github.com/msetzu/clusterlets
Project-URL: Bug Tracker, https://github.com/msetzu/clusterlets
Author-email: Mattia Setzu <setzu.mattia@gmail.com>
License-File: LICENSE
Classifier: Intended Audience :: Developers
Classifier: License :: OSI Approved :: GNU General Public License v3 or later (GPLv3+)
Classifier: Operating System :: OS Independent
Classifier: Programming Language :: Python :: 3.11
Requires-Python: <=3.13,>3.10
Requires-Dist: joblib>=1.0.0
Requires-Dist: more-itertools>=10.0.0
Requires-Dist: numpy>=2.0.0
Requires-Dist: scikit-learn>=1.0.0
Requires-Dist: scipy>=1.0.0
Requires-Dist: threadpoolctl==3.0.0
